sendqqmail.py
sendqqmail-0.2.dist-info/METADATA
sendqqmail-0.2.dist-info/WHEEL
sendqqmail-0.2.dist-info/top_level.txt
sendqqmail-0.2.dist-info/RECORD
