Metadata-Version: 2.1
Name: sendqqmail
Version: 0.2
Summary: A send QQ mail package
Home-page: UNKNOWN
Author: py3141
Author-email: 3386165598@qq.com
License: UNKNOWN
Platform: UNKNOWN
